schema_check/__init__.py
schema_check-0.1.0.dist-info/LICENSE
schema_check-0.1.0.dist-info/METADATA
schema_check-0.1.0.dist-info/WHEEL
schema_check-0.1.0.dist-info/RECORD
