Metadata-Version: 2.1
Name: schema-check
Version: 0.1.0
Summary: Define and enforce schema against user-provided JSON-like data
Home-page: https://github.com/glentner/schema-check
License: MIT
Keywords: data,validation
Author: Geoffrey Lentner
Author-email: glentner@purdue.edu
Requires-Python: >=3.10,<4.0
Classifier: Development Status :: 4 - Beta
Classifier: License :: OSI Approved :: MIT License
Classifier: Programming Language :: Python :: 3
Classifier: Programming Language :: Python :: 3.10
Classifier: Programming Language :: Python :: 3.11
Classifier: Programming Language :: Python :: 3.12
Project-URL: Documentation, https://github.com/glentner/schema-check
Project-URL: Repository, https://github.com/glentner/schema-check
